airtabledb/__init__.py
airtabledb/adapter.py
airtabledb/db_engine_specs.py
airtabledb/dialect.py
airtabledb/fields.py
airtabledb/formulas.py
airtabledb/lib.py
airtabledb/types.py
sqlalchemy_airtable-0.0.1.dev3.dist-info/LICENSE
sqlalchemy_airtable-0.0.1.dev3.dist-info/METADATA
sqlalchemy_airtable-0.0.1.dev3.dist-info/WHEEL
sqlalchemy_airtable-0.0.1.dev3.dist-info/entry_points.txt
sqlalchemy_airtable-0.0.1.dev3.dist-info/top_level.txt
sqlalchemy_airtable-0.0.1.dev3.dist-info/RECORD
