Metadata-Version: 2.1
Name: sqlalchemy-airtable
Version: 0.0.1.dev3
Summary: Python DB-API and SQLAlchemy interface for Airtable.
Home-page: https://github.com/cancan101/airtable-db-api
Author: Alex Rothberg
Author-email: agrothberg@gmail.com
License: MIT
Classifier: Development Status :: 2 - Pre-Alpha
Classifier: License :: OSI Approved :: MIT License
Classifier: Programming Language :: Python
Classifier: Programming Language :: Python :: 3.7
Classifier: Programming Language :: Python :: 3.8
Classifier: Programming Language :: Python :: 3.9
Classifier: Programming Language :: Python :: 3.10
Classifier: Programming Language :: Python :: 3.11
Classifier: Programming Language :: Python :: Implementation :: CPython
License-File: LICENSE
Requires-Dist: pyairtable
Requires-Dist: shillelagh (>=1.0.6)
Requires-Dist: typing-extensions
